varanus/.DS_Store
varanus/__init__.py
varanus/client/.DS_Store
varanus/client/__init__.py
varanus/client/apps.py
varanus/client/client.py
varanus/client/context.py
varanus/client/loggers.py
varanus/client/middleware.py
varanus/client/transport/.DS_Store
varanus/client/transport/__init__.py
varanus/client/transport/base.py
varanus/client/transport/database.py
varanus/client/transport/http.py
varanus/events.py
varanus/search/.DS_Store
varanus/search/__init__.py
varanus/search/base.py
varanus/search/fields.py
varanus/search/templates/search/.DS_Store
varanus/search/templates/search/daterange.html
varanus/search/templates/search/filter.html
varanus/search/templates/search/hidden.html
varanus/search/templates/search/multifacet.html
varanus/search/templates/search/search.html
varanus/search/utils.py
varanus/server/.DS_Store
varanus/server/__init__.py
varanus/server/__main__.py
varanus/server/admin.py
varanus/server/apps.py
varanus/server/asgi.py
varanus/server/context_processors.py
varanus/server/integrations/__init__.py
varanus/server/integrations/base.py
varanus/server/integrations/squish.py
varanus/server/management/__init__.py
varanus/server/management/commands/.DS_Store
varanus/server/management/commands/__init__.py
varanus/server/management/commands/maintenance.py
varanus/server/management/commands/migrateall.py
varanus/server/middleware.py
varanus/server/migrations/0001_initial.py
varanus/server/migrations/0002_drop_scheduledtask.py
varanus/server/migrations/0003_site_retention.py
varanus/server/migrations/0004_node_version.py
varanus/server/migrations/__init__.py
varanus/server/models.py
varanus/server/router.py
varanus/server/settings.py
varanus/server/static/.DS_Store
varanus/server/static/css/.DS_Store
varanus/server/static/css/varanus.css
varanus/server/static/js/.DS_Store
varanus/server/static/js/varanus.js
varanus/server/tasks.py
varanus/server/templates/.DS_Store
varanus/server/templates/base.html
varanus/server/templates/dashboard.html
varanus-0.1.0.dist-info/WHEEL
varanus-0.1.0.dist-info/METADATA
varanus-0.1.0.dist-info/RECORD
